README.txt
setup.cfg
setup.py
collective/__init__.py
collective.layout.authpersonalbar.egg-info/PKG-INFO
collective.layout.authpersonalbar.egg-info/SOURCES.txt
collective.layout.authpersonalbar.egg-info/dependency_links.txt
collective.layout.authpersonalbar.egg-info/entry_points.txt
collective.layout.authpersonalbar.egg-info/namespace_packages.txt
collective.layout.authpersonalbar.egg-info/not-zip-safe
collective.layout.authpersonalbar.egg-info/paster_plugins.txt
collective.layout.authpersonalbar.egg-info/requires.txt
collective.layout.authpersonalbar.egg-info/top_level.txt
collective/layout/__init__.py
collective/layout/authpersonalbar/README.txt
collective/layout/authpersonalbar/__init__.py
collective/layout/authpersonalbar/common.py
collective/layout/authpersonalbar/configure.zcml
collective/layout/authpersonalbar/interfaces.py
collective/layout/authpersonalbar/personal_bar_holder.pt
collective/layout/authpersonalbar/profiles/default/metadata.xml
collective/layout/authpersonalbar/profiles/default/viewlets.xml
collective/layout/authpersonalbar/tests/__init__.py
collective/layout/authpersonalbar/tests/_testing.py
collective/layout/authpersonalbar/tests/installation.txt
collective/layout/authpersonalbar/tests/test_doctests.py
docs/HISTORY.txt
docs/INSTALL.txt
docs/LICENSE.GPL
docs/LICENSE.txt