Metadata-Version: 1.0
Name: collective.layout.authpersonalbar
Version: 0.1
Summary: Show personal bar only to authenticated users.
Home-page: http://svn.plone.org/svn/collective/layout/authpersonalbar
Author: j23d
Author-email: j23d@dein-cms.de
License: GPL
Keywords: plone collective layout
Platform: UNKNOWN
Classifier: Framework :: Plone
Classifier: Programming Language :: Python
